hcsapi/__init__.py
hcsapi/crypto.py
hcsapi/hcs.py
hcsapi/keypad.py
hcsapi/mapping.py
hcsapi/request.py
hcsapi/seed.py
hcsapi/transkey.py
hcsapi-1.16.0.dist-info/LICENSE
hcsapi-1.16.0.dist-info/METADATA
hcsapi-1.16.0.dist-info/WHEEL
hcsapi-1.16.0.dist-info/top_level.txt
hcsapi-1.16.0.dist-info/RECORD
