Metadata-Version: 2.1
Name: hcsapi
Version: 1.16.0
Summary: 자가진단 자동화 비공식 Api (Automation tool for https://hcs.eduro.go.kr/)
Home-page: https://github.com/hcsapi/hcsapi
Download-URL: https://github.com/hcsapi/hcsapi
Author: scottjsh & excutetype
License: GPL-V3
Keywords: korea,covid,auto,hcs
Platform: UNKNOWN
Classifier: Programming Language :: Python :: 3.8
Classifier: License :: OSI Approved :: GNU General Public License v3 (GPLv3)
Classifier: Development Status :: 5 - Production/Stable
Requires-Python: >=3.4
License-File: LICENSE
Requires-Dist: aiohttp (==3.8.0)
Requires-Dist: pycryptodome (==3.11.0)
Requires-Dist: jwt (==1.3.1)
